fedartml/__init__.py
fedartml/fl_interactive_plots.py
fedartml/fl_split_as_federated_data.py
fedartml/function_base.py
FedArtML-0.1.34.dist-info/METADATA
FedArtML-0.1.34.dist-info/WHEEL
FedArtML-0.1.34.dist-info/top_level.txt
FedArtML-0.1.34.dist-info/RECORD
