Metadata-Version: 2.1
Name: FedArtML
Version: 0.1.34
Summary: Federated learning for Artificial Intelligence and Machine Learning library 
Home-page: 
Author: Daniel Mauricio Jimenez Gutierrez, Aris Anagnostopoulos, Ioannis Chatzigiannakis, Andrea Vitaletti
Author-email: jimenezgutierrez@diag.uniroma1.it
License: MIT
Classifier: Intended Audience :: Developers
Classifier: License :: OSI Approved :: MIT License
Classifier: Programming Language :: Python
Classifier: Programming Language :: Python :: 3
Classifier: Programming Language :: Python :: 3.7
Classifier: Programming Language :: Python :: 3.8
Classifier: Programming Language :: Python :: 3.9
Classifier: Programming Language :: Python :: 3.10
Classifier: Operating System :: OS Independent
Requires-Dist: numpy
Requires-Dist: ipywidgets
Requires-Dist: matplotlib
Requires-Dist: pandas
Requires-Dist: scipy
